{
  "id": "d6a06d00-82cb-429f-994a-26f95087c8c6",
  "title": "Broken Panel 7",
  "collectionId": "16730531-0705-470f-a154-788e5336708f",
  "category": "logo",
  "description": "A dark, high-contrast shader effect displaying a glowing green geometric shape against a pure black background. The central element is a glass-like component with a complex SVG-based shape rendered at 65% scale, featuring bright lime-green highlights (#4dff40) that create a neon glow effect. The shape appears to be pixelated with a scale of 50, creating a blocky, retro-digital aesthetic. Overlaid on the glass component are diagonal falling lines in bright green (#43df20 to #4ebe24) moving at a slow speed (0.25) at a 58-degree angle, creating a cascading matrix-like effect. The lines have a trail length of 0.15 and a stroke width of 0.76, producing thin streaks of light. A reflective plane effect at the bottom creates a subtle mirrored distortion with 4.7 blur and 0.59 distance falloff, suggesting depth and reflection. A dither pattern with bayer2 algorithm and 2-pixel size adds subtle noise texture throughout. The overall atmosphere is cyberpunk and digital, with a glass refraction effect (refraction value of 2) creating subtle light bending around the shape edges. The highlight color (#4dff40) dominates the visual with 0.8 intensity, creating a strong neon appearance. Edge softness of 0.2 provides slight anti-aliasing to the sharp geometric forms.",
  "thumbnail": "/shaders/thumbnails/d6a06d00-82cb-429f-994a-26f95087c8c6.webp",
  "config": {
    "components": [
      {
        "type": "SolidColor",
        "props": {
          "color": "#000000"
        }
      },
      {
        "type": "Glass",
        "props": {
          "aberration": 0,
          "cutout": true,
          "edgeSoftness": 0.2,
          "fresnel": 0,
          "fresnelSoftness": 0,
          "highlight": 0.8,
          "highlightColor": "#4dff40",
          "innerZoom": 1.2,
          "refraction": 2,
          "scale": 0.65,
          "shapeSdfUrl": "https://data.shaders.com/storage/v1/object/public/user-uploaded-images/user_33nh0FG48zZa0rIUZuK7vgwPfZe/UGhd-3-7xDaU_sdf.bin",
          "thickness": 0.24
        },
        "children": [
          {
            "type": "FallingLines",
            "props": {
              "angle": 58,
              "colorA": "#43df20",
              "colorB": "#4ebe24",
              "density": 60,
              "rounding": 0,
              "speed": 0.25,
              "speedVariance": 0.8,
              "strokeWidth": 0.76,
              "trailLength": 0.15
            }
          },
          {
            "type": "Pixelate",
            "props": {
              "visible": true
            }
          }
        ]
      },
      {
        "type": "Dither",
        "props": {
          "colorMode": "source",
          "pattern": "bayer2",
          "pixelSize": 2
        }
      },
      {
        "type": "ReflectivePlane",
        "props": {
          "blur": 4.7,
          "blurDistance": 0.14,
          "distance": 0.59,
          "falloff": 1.91,
          "height": 0.75
        }
      }
    ]
  },
  "colorSpace": "p3-linear",
  "toneMapping": "aces"
}