{
  "id": "f7dace04-cd20-47f2-af7d-c2f491dbc476",
  "title": "Swirling Gradient 10",
  "collectionId": "5b4580ec-38eb-4986-9867-4a5ae2965a1b",
  "category": "background",
  "description": "A dynamic swirl shader effect featuring concentric curved bands that radiate outward in a hypnotic pattern. The primary visual consists of alternating stripes of bright neon green (#01dd06) and deep purple (#7246ad) that flow in smooth, organic curves creating a sense of rotational motion. The swirl pattern originates from the center-left area and expands outward with graceful, wave-like distortions. Overlaid on top is a ConcentricSpin component generating 9 concentric rings that add rhythmic circular structure to the composition, with the rings centered slightly off-center (at coordinates 0, 1). The effect has a subtle paper texture grain applied across the entire surface, creating a tactile, slightly roughened appearance that breaks up the smoothness of the gradients. The edges fade to transparency, and the overall blend mode is normal with full opacity. The color interpolation uses the oklab color space, resulting in perceptually smooth transitions between the vibrant green and purple hues. The combination creates a mesmerizing, almost liquid-like visual with a modern, digital aesthetic that suggests movement and energy despite being a static composition.",
  "thumbnail": "/shaders/thumbnails/f7dace04-cd20-47f2-af7d-c2f491dbc476.webp",
  "config": {
    "components": [
      {
        "type": "Swirl",
        "props": {
          "blend": {
            "axis": "x",
            "type": "mouse",
            "momentum": 0.2,
            "outputMax": 60,
            "outputMin": 40,
            "smoothing": 0.6
          },
          "colorA": "#7246ad",
          "colorB": "#01dd06",
          "colorSpace": "oklab",
          "detail": 1.2
        }
      },
      {
        "type": "ConcentricSpin",
        "props": {
          "center": {
            "x": 0,
            "y": 1
          },
          "rings": 9,
          "smoothness": 0.76,
          "speed": -1.2,
          "speedRandomness": 0.14
        }
      },
      {
        "type": "Paper",
        "props": {
          "roughness": 0.2
        }
      }
    ]
  },
  "colorSpace": "p3-linear",
  "toneMapping": "aces"
}