{
  "name": "TiltShift",
  "category": "Blurs",
  "description": "Selective focus blur mimicking tilt-shift photography",
  "requiresChild": true,
  "requiresRTT": true,
  "props": {
    "intensity": {
      "default": 50,
      "description": "Maximum blur intensity at edges",
      "ui": {
        "type": [
          "range",
          "map"
        ],
        "min": 0,
        "max": 100,
        "step": 1,
        "label": "Intensity",
        "group": "Effect"
      }
    },
    "width": {
      "default": 0.3,
      "description": "Width of the sharp focus area",
      "ui": {
        "type": [
          "range",
          "map"
        ],
        "min": 0,
        "max": 1,
        "step": 0.1,
        "label": "Width",
        "group": "Effect"
      }
    },
    "falloff": {
      "default": 0.3,
      "description": "Distance over which blur transitions to full strength",
      "ui": {
        "type": [
          "range",
          "map"
        ],
        "min": 0,
        "max": 1,
        "step": 0.1,
        "label": "Falloff",
        "group": "Effect"
      }
    },
    "angle": {
      "default": 0,
      "description": "Rotation angle of the focus line (in degrees)",
      "ui": {
        "type": [
          "range",
          "map"
        ],
        "min": 0,
        "max": 360,
        "step": 1,
        "label": "Angle",
        "group": "Effect"
      }
    },
    "center": {
      "default": {
        "x": 0.5,
        "y": 0.5
      },
      "description": "Center point of the focus line",
      "ui": {
        "type": "position",
        "label": "Center",
        "group": "Position"
      }
    }
  }
}